snaptrade/__init__.py
snaptrade/utils.py
snaptrade/api_client/__init__.py
snaptrade/api_client/endpoints.json
snaptrade/api_client/snaptrade_api_client.py
tests/__init__.py
snaptrade-1.1.0.dist-info/LICENSE
snaptrade-1.1.0.dist-info/METADATA
snaptrade-1.1.0.dist-info/WHEEL
snaptrade-1.1.0.dist-info/top_level.txt
snaptrade-1.1.0.dist-info/RECORD
