Metadata-Version: 2.1
Name: snaptrade
Version: 1.1.0
Summary: A Python implementation of SnapTrade API client library
Classifier: Development Status :: 7 - Inactive
Classifier: License :: OSI Approved :: Apache Software License
Classifier: Programming Language :: Python :: 3.6
Classifier: Programming Language :: Python :: 3.7
Classifier: Programming Language :: Python :: 3.8
Classifier: Programming Language :: Python :: 3.9
Classifier: Programming Language :: Python :: 3.10
Classifier: Programming Language :: Python :: 3.11
License-File: LICENSE
Requires-Dist: requests
Requires-Dist: pycryptodome
